robozilla/__init__.py
robozilla/__main__.py
robozilla/bz.py
robozilla/constants.py
robozilla/parser.py
robozilla/scan.py
robozilla/decorators/__init__.py
robozilla/filters/__init__.py
robozilla/filters/base.py
robozilla/filters/decorator.py
robozilla/filters/isopen.py
robozilla/providers/__init__.py
robozilla/providers/fs.py
robozilla/query/__init__.py
robozilla/query/exp.py
robozilla/query/query.py
robozilla/reporters/__init__.py
robozilla/reporters/base.py
robozilla-0.2.7.dist-info/LICENSE
robozilla-0.2.7.dist-info/METADATA
robozilla-0.2.7.dist-info/WHEEL
robozilla-0.2.7.dist-info/entry_points.txt
robozilla-0.2.7.dist-info/top_level.txt
robozilla-0.2.7.dist-info/RECORD
