Metadata-Version: 2.1
Name: robozilla
Version: 0.2.7
Summary: Robottelo Bugzilla Parser
Home-page: https://github.com/ldjebran/robozilla
Author: Djebran Lezzoum
Author-email: ldjebran@gmail.com
License: GNU General Public License v3 (GPLv3)
Keywords: robozilla
Classifier: Development Status :: 2 - Pre-Alpha
Classifier: Intended Audience :: Developers
Classifier: License :: OSI Approved :: GNU General Public License v3 (GPLv3)
Classifier: Natural Language :: English
Classifier: Programming Language :: Python :: 2
Classifier: Programming Language :: Python :: 2.7
Classifier: Programming Language :: Python :: 3
Classifier: Programming Language :: Python :: 3.5
License-File: LICENSE
Requires-Dist: Click (>=6.0)
Requires-Dist: python-bugzilla
Requires-Dist: six
